setup.py
ohad1234/__init__.py
ohad1234.egg-info/PKG-INFO
ohad1234.egg-info/SOURCES.txt
ohad1234.egg-info/dependency_links.txt
ohad1234.egg-info/not-zip-safe
ohad1234.egg-info/top_level.txt